[ { "editorData": { }, "mapName": "KillLevel 03", "mapAuthor": "JoshuaHarding2", "authorTime": 4.97, "goldTime": 10.00, "silverTime": 30.00, "bronzeTime": 100.00 }, { "start": { "x": -5, "y": -2.5, "z": 0 }, "end": { "x": 5, "y": -2, "z": 10 }, "type": "regular" }, { "start": { "x": -5, "y": -2.5, "z": -10 }, "end": { "x": 5, "y": -2, "z": 0 }, "type": "kill" }, { "start": { "x": -5, "y": -2.5, "z": -20 }, "end": { "x": 5, "y": -2, "z": -10 }, "type": "kill" }, { "start": { "x": -15, "y": -2.5, "z": -20 }, "end": { "x": -5, "y": -2, "z": -10 }, "type": "kill" }, { "start": { "x": -15, "y": -2.5, "z": -10 }, "end": { "x": -5, "y": -2, "z": 0 }, "type": "regular" }, { "start": { "x": -25, "y": -2.5, "z": -10 }, "end": { "x": -15, "y": -2, "z": 0 }, "type": "kill" }, { "start": { "x": -25, "y": -2.5, "z": -20 }, "end": { "x": -15, "y": -2, "z": -10 }, "type": "kill" }, { "start": { "x": -25, "y": -2.5, "z": -30 }, "end": { "x": -15, "y": -2, "z": -20 }, "type": "kill" }, { "start": { "x": -15, "y": -2.5, "z": -30 }, "end": { "x": -5, "y": -2, "z": -20 }, "type": "regular" }, { "start": { "x": -5, "y": -2.5, "z": -30 }, "end": { "x": 5, "y": -2, "z": -20 }, "type": "kill" }, { "start": { "x": 5, "y": -2.5, "z": -30 }, "end": { "x": 15, "y": -2, "z": -20 }, "type": "kill" }, { "start": { "x": 5, "y": -2.5, "z": -20 }, "end": { "x": 15, "y": -2, "z": -10 }, "type": "kill" }, { "start": { "x": 5, "y": -2.5, "z": -10 }, "end": { "x": 15, "y": -2, "z": 0 }, "type": "regular" }, { "start": { "x": -5, "y": -2, "z": 0 }, "end": { "x": -4.5, "y": 5, "z": 10 }, "type": "kill" }, { "start": { "x": 5, "y": -2, "z": 0 }, "end": { "x": 5.5, "y": 5, "z": 10 }, "type": "kill" }, { "start": { "x": -5, "y": -2, "z": -10 }, "end": { "x": -4.5, "y": 5, "z": 0 }, "type": "kill" }, { "start": { "x": 5, "y": -2, "z": -10 }, "end": { "x": 5.5, "y": 5, "z": 0 }, "type": "kill" }, { "start": { "x": -5, "y": -2, "z": 10 }, "end": { "x": 5, "y": 5, "z": 9.5 }, "type": "kill" }, { "start": { "x": 5, "y": -2, "z": -20 }, "end": { "x": 5.5, "y": 5, "z": -10 }, "type": "kill" }, { "start": { "x": -5, "y": -2, "z": -20 }, "end": { "x": 5, "y": 5, "z": -20.5 }, "type": "kill" }, { "start": { "x": -15, "y": -2, "z": -20 }, "end": { "x": -5, "y": 5, "z": -20.5 }, "type": "kill" }, { "start": { "x": -15, "y": -2, "z": -20 }, "end": { "x": -14.5, "y": 5, "z": -10 }, "type": "kill" }, { "start": { "x": -15, "y": -2, "z": 0 }, "end": { "x": -5, "y": 5, "z": -0.5 }, "type": "kill" }, { "start": { "x": -25, "y": -2, "z": 0 }, "end": { "x": -15, "y": 5, "z": -0.5 }, "type": "kill" }, { "start": { "x": -25, "y": -2, "z": -10 }, "end": { "x": -24.5, "y": 5, "z": 0 }, "type": "kill" }, { "start": { "x": -25, "y": -2, "z": -20 }, "end": { "x": -24.5, "y": 5, "z": -10 }, "type": "kill" }, { "start": { "x": -25, "y": -2, "z": -30 }, "end": { "x": -24.5, "y": 5, "z": -20 }, "type": "kill" }, { "start": { "x": -25, "y": -2, "z": -30 }, "end": { "x": -15, "y": 5, "z": -30.5 }, "type": "kill" }, { "start": { "x": -15, "y": -2, "z": -30 }, "end": { "x": -5, "y": 5, "z": -30.5 }, "type": "kill" }, { "start": { "x": -5, "y": -2, "z": -30 }, "end": { "x": 5, "y": 5, "z": -30.5 }, "type": "kill" }, { "start": { "x": 15, "y": -2, "z": -20 }, "end": { "x": 15.5, "y": 5, "z": -10 }, "type": "kill" }, { "start": { "x": 15, "y": -2, "z": -30 }, "end": { "x": 15.5, "y": 5, "z": -20 }, "type": "kill" }, { "start": { "x": 5, "y": -2, "z": -30 }, "end": { "x": 15, "y": 5, "z": -30.5 }, "type": "kill" }, { "start": { "x": 5, "y": -2, "z": 0 }, "end": { "x": 15, "y": 5, "z": -0.5 }, "type": "kill" }, { "start": { "x": 15, "y": -2, "z": 0 }, "end": { "x": 25, "y": 5, "z": -0.5 }, "type": "kill" }, { "start": { "x": 15, "y": -2, "z": 10 }, "end": { "x": 25, "y": 5, "z": 9.5 }, "type": "end" } ]